matmulbench/__init__.py
matmulbench/common/__init__.py
matmulbench/common/timing.py
matmulbench/common/utils.py
matmulbench/naive/__init__.py
matmulbench/naive/python/__init__.py
matmulbench/naive/python/interpreter/__init__.py
matmulbench/naive/python/interpreter/basic/__init__.py
matmulbench/naive/python/interpreter/basic/main.py
matmulbench/naive/python/interpreter/basic/randutils.py
matmulbench/naive/python/interpreter/basic/utils.py
matmulbench-0.1.5.dist-info/WHEEL
matmulbench-0.1.5.dist-info/METADATA
matmulbench-0.1.5.dist-info/RECORD
