Metadata-Version: 2.3
Name: matmulbench
Version: 0.1.5
Summary: The idea is primarily to get me to write matmul code and compare with my own eyes the difference across languages.
Author: Kosaksi Pasappugazh
Author-email: Kosaksi Pasappugazh <pasappugazhk@gmail.com>
License: MIT
Requires-Dist: numpy>=2.3.2
Requires-Python: >=3.12
